COPYING
MANIFEST.in
README
health_qrcodes_report.xml
health_qrcodes_view.xml
setup.py
./__init__.py
./health_qrcodes.py
./health_qrcodes_report.xml
./health_qrcodes_view.xml
./tryton.cfg
./doc/index.rst
./locale/ar.po
./locale/de.po
./locale/el.po
./locale/es.po
./locale/fr.po
./locale/it_IT.po
./locale/ja_JP.po
./locale/lo.po
./locale/pt_BR.po
./locale/zh_CN.po
./report/appointment_qrcode.odt
./report/barcode39.odt
./report/labtest_qrcode.odt
./report/newborn_card.odt
./report/patient_card.odt
./tests/__init__.py
./tests/test_health_qrcodes.py
./view/gnuhealth_appointment.xml
./view/gnuhealth_patient_form.xml
./view/newborn_form.xml
locale/ar.po
locale/de.po
locale/el.po
locale/es.po
locale/fr.po
locale/it_IT.po
locale/ja_JP.po
locale/lo.po
locale/pt_BR.po
locale/zh_CN.po
report/appointment_qrcode.odt
report/barcode39.odt
report/labtest_qrcode.odt
report/newborn_card.odt
report/patient_card.odt
trytond_health_qrcodes.egg-info/PKG-INFO
trytond_health_qrcodes.egg-info/SOURCES.txt
trytond_health_qrcodes.egg-info/dependency_links.txt
trytond_health_qrcodes.egg-info/entry_points.txt
trytond_health_qrcodes.egg-info/not-zip-safe
trytond_health_qrcodes.egg-info/requires.txt
trytond_health_qrcodes.egg-info/top_level.txt
view/gnuhealth_appointment.xml
view/gnuhealth_patient_form.xml
view/newborn_form.xml